swarmauri_distance_minkowski/MinkowskiDistance.py
swarmauri_distance_minkowski/__init__.py
swarmauri_distance_minkowski-0.7.5.dist-info/LICENSE
swarmauri_distance_minkowski-0.7.5.dist-info/METADATA
swarmauri_distance_minkowski-0.7.5.dist-info/WHEEL
swarmauri_distance_minkowski-0.7.5.dist-info/entry_points.txt
swarmauri_distance_minkowski-0.7.5.dist-info/RECORD
